todomd/__init__.py
todomd/__main__.py
todomdcli-0.0.1.dist-info/LICENSE
todomdcli-0.0.1.dist-info/METADATA
todomdcli-0.0.1.dist-info/WHEEL
todomdcli-0.0.1.dist-info/top_level.txt
todomdcli-0.0.1.dist-info/RECORD
