Metadata-Version: 2.1
Name: todomdcli
Version: 0.0.1
Summary: TUI Todo Application, that converts all your records into pretty markdown
Author-email: Alex Zolotarov <alex@zolotarov.me>
Requires-Python: >=3.9
License-File: LICENSE
Requires-Dist: fire
